hoppr_cyclonedx_models/__init__.py
hoppr_cyclonedx_models/base.py
hoppr_cyclonedx_models/cyclonedx_1_3.py
hoppr_cyclonedx_models/cyclonedx_1_4.py
hoppr_cyclonedx_models/cyclonedx_1_5.py
hoppr_cyclonedx_models/cyclonedx_1_6.py
hoppr_cyclonedx_models/py.typed
hoppr_cyclonedx_models/spdx.py
hoppr_cyclonedx_models-0.7.0.dist-info/METADATA
hoppr_cyclonedx_models-0.7.0.dist-info/WHEEL
hoppr_cyclonedx_models-0.7.0.dist-info/licenses/LICENSE
hoppr_cyclonedx_models-0.7.0.dist-info/RECORD
