Metadata-Version: 2.4
Name: hoppr-cyclonedx-models
Version: 0.7.0
Summary: CycloneDX Pydantic models for easy use in your Python project.
License: MIT
License-File: LICENSE
Keywords: pydantic,models,cyclonedx,software bill of materials
Author: LMCO Open Source
Author-email: open.source@lmco.com
Requires-Python: >=3.8.0,<4.0.0
Classifier: Development Status :: 2 - Pre-Alpha
Classifier: Framework :: Pydantic
Classifier: Framework :: Pytest
Classifier: Intended Audience :: Developers
Classifier: License :: OSI Approved :: MIT License
Classifier: Programming Language :: Python :: 3
Classifier: Programming Language :: Python :: 3.8
Classifier: Programming Language :: Python :: 3.9
Classifier: Programming Language :: Python :: 3.10
Classifier: Programming Language :: Python :: 3.11
Classifier: Programming Language :: Python :: 3.12
Classifier: Programming Language :: Python :: 3.13
Classifier: Programming Language :: Python :: 3.14
Classifier: Topic :: Software Development :: Code Generators
Classifier: Typing :: Typed
Requires-Dist: pydantic[email] (>=1.10.2,<2.0.0)
Requires-Dist: typing-extensions (>=4.7.1,<5.0.0)
Project-URL: Repository, https://gitlab.com/hoppr/hoppr-cyclonedx-models
